odoo10_addon_base_unece-10.0.1.0.0-py2.7-nspkg.pth
odoo10_addon_base_unece-10.0.1.0.0.dist-info/top_level.txt
odoo10_addon_base_unece-10.0.1.0.0.dist-info/WHEEL
odoo10_addon_base_unece-10.0.1.0.0.dist-info/RECORD
odoo10_addon_base_unece-10.0.1.0.0.dist-info/metadata.json
odoo10_addon_base_unece-10.0.1.0.0.dist-info/DESCRIPTION.rst
odoo10_addon_base_unece-10.0.1.0.0.dist-info/METADATA
odoo10_addon_base_unece-10.0.1.0.0.dist-info/namespace_packages.txt
odoo/addons/base_unece/__manifest__.py
odoo/addons/base_unece/__init__.py
odoo/addons/base_unece/README.rst
odoo/addons/base_unece/security/ir.model.access.csv
odoo/addons/base_unece/models/unece_code_list.py
odoo/addons/base_unece/models/__init__.py
odoo/addons/base_unece/views/unece_code_list.xml
